batchglm/__init__.py
batchglm/_version.py
batchglm/data.py
batchglm/log_cfg.py
batchglm/pkg_constants.py
batchglm/api/__init__.py
batchglm/api/data.py
batchglm/api/typing.py
batchglm/api/models/__init__.py
batchglm/api/models/numpy/__init__.py
batchglm/api/models/numpy/glm_nb.py
batchglm/api/models/tf1/__init__.py
batchglm/api/models/tf1/glm_beta.py
batchglm/api/models/tf1/glm_nb.py
batchglm/api/models/tf1/glm_norm.py
batchglm/api/models/tf2/__init__.py
batchglm/api/models/tf2/glm_beta.py
batchglm/api/models/tf2/glm_nb.py
batchglm/api/models/tf2/glm_norm.py
batchglm/api/utils/__init__.py
batchglm/api/utils/linalg.py
batchglm/models/__init__.py
batchglm/models/base/__init__.py
batchglm/models/base/estimator.py
batchglm/models/base/external.py
batchglm/models/base/input.py
batchglm/models/base/model.py
batchglm/models/base/simulator.py
batchglm/models/base_glm/__init__.py
batchglm/models/base_glm/estimator.py
batchglm/models/base_glm/external.py
batchglm/models/base_glm/input.py
batchglm/models/base_glm/model.py
batchglm/models/base_glm/simulator.py
batchglm/models/base_glm/utils.py
batchglm/models/glm_beta/__init__.py
batchglm/models/glm_beta/external.py
batchglm/models/glm_beta/model.py
batchglm/models/glm_beta/simulator.py
batchglm/models/glm_beta/utils.py
batchglm/models/glm_nb/__init__.py
batchglm/models/glm_nb/external.py
batchglm/models/glm_nb/model.py
batchglm/models/glm_nb/simulator.py
batchglm/models/glm_nb/utils.py
batchglm/models/glm_norm/__init__.py
batchglm/models/glm_norm/external.py
batchglm/models/glm_norm/model.py
batchglm/models/glm_norm/simulator.py
batchglm/models/glm_norm/utils.py
batchglm/train/__init__.py
batchglm/train/numpy/__init__.py
batchglm/train/numpy/base_glm/__init__.py
batchglm/train/numpy/base_glm/estimator.py
batchglm/train/numpy/base_glm/external.py
batchglm/train/numpy/base_glm/model.py
batchglm/train/numpy/base_glm/processModel.py
batchglm-0.7.4.dist-info/METADATA
batchglm-0.7.4.dist-info/RECORD
batchglm-0.7.4.dist-info/WHEEL
batchglm-0.7.4.dist-info/top_level.txt
