Metadata-Version: 2.1
Name: batchglm
Version: 0.7.4
Summary: Fast and scalable fitting of over-determined generalized-linear models (GLMs)
Home-page: UNKNOWN
Author: David S. Fischer, Florian R. Hölzlwimmer, Sabrina Richter
Author-email: david.fischer@helmholtz-muenchen.de
License: UNKNOWN
Platform: UNKNOWN
Provides-Extra: docs
Provides-Extra: plotting_deps
Provides-Extra: optional
Requires-Dist: anndata
Requires-Dist: numpy (>=1.16.4)
Requires-Dist: scipy (>=1.2.1)
Requires-Dist: pandas
Requires-Dist: dask
Requires-Dist: toolz
Requires-Dist: patsy
Requires-Dist: sparse
Requires-Dist: dask
Provides-Extra: docs
Requires-Dist: sphinx; extra == 'docs'
Requires-Dist: sphinx-autodoc-typehints; extra == 'docs'
Requires-Dist: sphinx-rtd-theme; extra == 'docs'
Requires-Dist: jinja2; extra == 'docs'
Requires-Dist: docutils; extra == 'docs'
Provides-Extra: optional
Requires-Dist: tensorflow (>=1.14.0); extra == 'optional'
Requires-Dist: tensorflow-gpu (>=1.14.0); extra == 'optional'
Provides-Extra: plotting_deps
Requires-Dist: matplotlib; extra == 'plotting_deps'
Requires-Dist: seaborn; extra == 'plotting_deps'
